django_clerk/__about__.py
django_clerk/__init__.py
django_clerk/admin.py
django_clerk/apps.py
django_clerk/jwt.py
django_clerk/middleware.py
django_clerk/models.py
django_clerk/tests.py
django_clerk/views.py
django_clerk/migrations/0001_initial.py
django_clerk/migrations/__init__.py
django_clerk-0.1.15.dist-info/METADATA
django_clerk-0.1.15.dist-info/WHEEL
django_clerk-0.1.15.dist-info/licenses/LICENSE
django_clerk-0.1.15.dist-info/licenses/LICENSE.txt
django_clerk-0.1.15.dist-info/RECORD
