Metadata-Version: 2.1
Name: django-clerk
Version: 0.1.15
Summary: Django Integration for Clerk Auth Platform
Project-URL: Documentation, https://github.com/yesawoo/django-clerk#readme
Project-URL: Issues, https://github.com/yesawoo/django-clerk/issues
Project-URL: Source, https://github.com/yesawoo/django-clerk
Author-email: James Thigpen <james.r.thigpen@gmail.com>
License-Expression: MIT
License-File: LICENSE
License-File: LICENSE.txt
Classifier: Development Status :: 3 - Alpha
Classifier: Programming Language :: Python
Classifier: Programming Language :: Python :: 3.8
Classifier: Programming Language :: Python :: 3.9
Classifier: Programming Language :: Python :: 3.10
Classifier: Programming Language :: Python :: 3.11
Classifier: Programming Language :: Python :: 3.12
Classifier: Programming Language :: Python :: Implementation :: CPython
Requires-Python: >=3.8
Requires-Dist: django>=4.0
Requires-Dist: pyjwt>=2.8
Requires-Dist: svix
